odoo/addons/html_text/README.rst
odoo/addons/html_text/__init__.py
odoo/addons/html_text/__manifest__.py
odoo/addons/html_text/i18n/ca.po
odoo/addons/html_text/i18n/de.po
odoo/addons/html_text/i18n/es.po
odoo/addons/html_text/i18n/es_AR.po
odoo/addons/html_text/i18n/es_ES.po
odoo/addons/html_text/i18n/hr.po
odoo/addons/html_text/i18n/html_text.pot
odoo/addons/html_text/i18n/it.po
odoo/addons/html_text/i18n/tr.po
odoo/addons/html_text/i18n/zh_CN.po
odoo/addons/html_text/models/__init__.py
odoo/addons/html_text/models/ir_fields_converter.py
odoo/addons/html_text/readme/CONTRIBUTORS.md
odoo/addons/html_text/readme/DESCRIPTION.md
odoo/addons/html_text/readme/ROADMAP.md
odoo/addons/html_text/readme/USAGE.md
odoo/addons/html_text/static/description/icon.png
odoo/addons/html_text/static/description/index.html
odoo/addons/html_text/tests/__init__.py
odoo/addons/html_text/tests/test_extractor.py
odoo_addon_html_text-18.0.1.0.0.3.dist-info/METADATA
odoo_addon_html_text-18.0.1.0.0.3.dist-info/WHEEL
odoo_addon_html_text-18.0.1.0.0.3.dist-info/top_level.txt
odoo_addon_html_text-18.0.1.0.0.3.dist-info/RECORD
