Metadata-Version: 2.1
Name: odoo-addon-html_text
Version: 18.0.1.0.0.3
Requires-Python: >=3.10
Requires-Dist: odoo==18.0.*
Summary: Generate excerpts from any HTML field
Home-page: https://github.com/OCA/server-tools
License: AGPL-3
Author: =?utf-8?q?Grupo_ESOC_Ingenier=C3=ADa_de_Servicios=2C_Tecnativa=2C_Onestein=2C_Odoo_Community_Association_=28OCA=29?=
Author-email: support@odoo-community.org
Classifier: Programming Language :: Python
Classifier: Framework :: Odoo
Classifier: Framework :: Odoo :: 18.0
Classifier: License :: OSI Approved :: GNU Affero General Public License v3
